Full Adder using half adder/khalf_adder.v
module khalf_adder(
    a,b,c,
    sum,c_out
);
    input wire a,b,c;
    output wire sum,c_out;

    //assign (sum,c_out) = a + b;
    assign sum = a ^ b;
    assign c_out = a & b;
    
endmodule

Full Adder using half adder/khalf_adder_tb.v
`timescale 1ns/1ns
//`include "khalf_adder.v"
module khalf_adder_tb;
initial begin
$dumpfile("test.vcd");
$dumpvars(0,khalf_adder_tb);

end 

reg a_tb,b_tb, c_tb;
wire sum1_tb, sum2_tb,c_out_tb, c_out1_tb, c_out2_tb;

khalf_adder khalf_adder_1 (
    .a(a_tb),
    .b(b_tb),
    .c(c_tb),
    .sum(sum1_tb),
    .c_out(c_out1_tb)
);
khalf_adder khalf_adder_2 (
    .a(sum1_tb),
    .b(c_tb),
    .c(c_tb),
    .sum(sum2_tb),
    .c_out(c_out2_tb)
);

assign c_out_tb = c_out1_tb | c_out2_tb;

initial begin
        a_tb = 1'b0;
        b_tb = 1'b0;
        c_tb = 1'b0;
        #5
        a_tb = 1'b0;
        b_tb = 1'b0;
        c_tb = 1'b1;
        #5
        a_tb = 1'b0;
        b_tb = 1'b1;
        c_tb = 1'b0;
        #5
        a_tb = 1'b0;
        b_tb = 1'b1;
        c_tb = 1'b1;
        #5
        a_tb = 1'b1;
        b_tb = 1'b0;
        c_tb = 1'b0;
        #5
        a_tb = 1'b1;
        b_tb = 1'b0;
        c_tb = 1'b1;
        #5
        a_tb = 1'b1;
        b_tb = 1'b1;
        c_tb = 1'b0;
        #5
        a_tb = 1'b1;
        b_tb = 1'b1;
        c_tb = 1'b1;
        #5
        #40
        $finish;
    end

endmodule

Full Adder using half adder/test.vcd
$date
	Mon May 10 19:42:53 2021
$end
$version
	Icarus Verilog
$end
$timescale
	1ns
$end
$scope module khalf_adder_tb $end
$var wire 1 ! c_out_tb $end
$var wire 1 " sum2_tb $end
$var wire 1 # sum1_tb $end
$var wire 1 $ c_out2_tb $end
$var wire 1 % c_out1_tb $end
$var reg 1 & a_tb $end
$var reg 1 ' b_tb $end
$var reg 1 ( c_tb $end
$scope module khalf_adder_1 $end
$var wire 1 & a $end
$var wire 1 ' b $end
$var wire 1 ( c $end
$var wire 1 % c_out $end
$var wire 1 # sum $end
$upscope $end
$scope module khalf_adder_2 $end
$var wire 1 # a $end
$var wire 1 ( b $end
$var wire 1 ( c $end
$var wire 1 $ c_out $end
$var wire 1 " sum $end
$upscope $end
$upscope $end
$enddefinitions $end
#0
$dumpvars
0(
0'
0&
0%
0$
0#
0"
0!
$end
#5
1"
1(
#10
1#
0(
1'
#15
1!
0"
1$
1(
#20
0!
1"
0$
0(
0'
1&
#25
1!
0"
1$
1(
#30
0$
0#
1%
0(
1'
#35
1"
1(
